django_simplesshkey-1.1.0.dist-info/DESCRIPTION.rst
django_simplesshkey-1.1.0.dist-info/METADATA
django_simplesshkey-1.1.0.dist-info/RECORD
django_simplesshkey-1.1.0.dist-info/WHEEL
django_simplesshkey-1.1.0.dist-info/metadata.json
django_simplesshkey-1.1.0.dist-info/top_level.txt
simplesshkey/__init__.py
simplesshkey/admin.py
simplesshkey/forms.py
simplesshkey/models.py
simplesshkey/settings.py
simplesshkey/tests.py
simplesshkey/urls.py
simplesshkey/util.py
simplesshkey/views.py
simplesshkey/migrations/0001_initial.py
simplesshkey/migrations/0002_auto_20170611_1547.py
simplesshkey/migrations/0003_userkey_keytype.py
simplesshkey/migrations/0004_auto_20180325_1420.py
simplesshkey/migrations/__init__.py
simplesshkey/templates.example/sshkey/add_key.html
simplesshkey/templates.example/sshkey/add_key.txt
simplesshkey/templates.example/sshkey/userkey_detail.html
simplesshkey/templates.example/sshkey/userkey_list.html
