Metadata-Version: 2.0
Name: django-simplesshkey
Version: 1.1.0
Summary: Associates multiple SSH public keys with Django user accounts (fork of django-sshkey without SSHD integration)
Home-page: https://github.com/zorun/django-simplesshkey
Author: Baptiste Jonglez
Author-email: python@bitsofnetworks.org
License: BSD
Platform: UNKNOWN
Classifier: Environment :: Web Environment
Classifier: Framework :: Django
Classifier: Intended Audience :: Developers
Classifier: License :: OSI Approved :: BSD License
Classifier: Operating System :: OS Independent
Classifier: Programming Language :: Python
Classifier: Programming Language :: Python :: 2.7
Classifier: Programming Language :: Python :: 3.3
Classifier: Programming Language :: Python :: 3.4
Classifier: Programming Language :: Python :: 3.5
Classifier: Programming Language :: Python :: 3.6
Classifier: Topic :: Internet :: WWW/HTTP
Classifier: Topic :: Internet :: WWW/HTTP :: Dynamic Content
Requires-Dist: pyasn1
